xp_tool/__init__.py
xp_tool/async_call_ai.py
xp_tool/call_ai.py
xp_tool/data_email_exporters.py
xp_tool/oss_storage_handlers.py
xp_tool/rag_knowledge_base.py
xp_tool/schema_builder.py
xp_tool/txt_tool.py
xp_tool-2.0.dist-info/METADATA
xp_tool-2.0.dist-info/WHEEL
xp_tool-2.0.dist-info/top_level.txt
xp_tool-2.0.dist-info/RECORD
