Metadata-Version: 2.1
Name: xp_tool
Version: 2.0
Summary: xp_tool
Home-page: 
Author: XuPeng
Author-email: xupeng23456@126.com
License: MIT
Classifier: License :: OSI Approved :: MIT License
Classifier: Programming Language :: Python
Classifier: Programming Language :: Python :: 3
Classifier: Programming Language :: Python :: 3.6
Classifier: Programming Language :: Python :: Implementation :: CPython
Classifier: Programming Language :: Python :: Implementation :: PyPy
Requires-Python: >=3.10.0
Requires-Dist: openai
Requires-Dist: pandas
Requires-Dist: oss2
Requires-Dist: python-dotenv
Requires-Dist: PyPDF2
Requires-Dist: langchain-text-splitters
Requires-Dist: sentence-transformers
Requires-Dist: numpy
Requires-Dist: faiss-cpu
Requires-Dist: dashscope
